LICENSE
README.md
setup.py
easyenvi/__init__.py
easyenvi/easy_environment.py
easyenvi.egg-info/PKG-INFO
easyenvi.egg-info/SOURCES.txt
easyenvi.egg-info/dependency_links.txt
easyenvi.egg-info/requires.txt
easyenvi.egg-info/top_level.txt
easyenvi/envs/__init__.py
easyenvi/envs/disk.py
easyenvi/envs/gcloud.py
easyenvi/envs/sharepoint.py
easyenvi/error_handler/__init__.py
easyenvi/error_handler/error_handler.py
easyenvi/file/__init__.py
easyenvi/file/file_manager.py
easyenvi/file/format_converter.py
tests/test_big_query.py
tests/test_google_cloud_storage.py
tests/test_local_save_load.py
tests/test_sharepoint.py