Metadata-Version: 2.1
Name: easyenvi
Version: 1.0.8
Summary: Easy-to-use functionality for managing files and data in different environments
Home-page: https://github.com/AntoinePinto/easyenvi
Author: Antoine PINTO
Author-email: antoine.pinto1@outlook.fr
License: MIT
Project-URL: Documentation, https://antoinepinto.gitbook.io/easyenvi/
Project-URL: Source Code, https://github.com/AntoinePinto/easyenvi
Keywords: file-manager,easy-to-use,environment,cloud,gcp,sharepoint
Requires-Python: >=3.7
License-File: LICENSE
Requires-Dist: fsspec>=2023.1.0
